SimpleTornadoServer.py
setup.py
SimpleTornadoServer.egg-info/PKG-INFO
SimpleTornadoServer.egg-info/SOURCES.txt
SimpleTornadoServer.egg-info/dependency_links.txt
SimpleTornadoServer.egg-info/not-zip-safe
SimpleTornadoServer.egg-info/requires.txt
SimpleTornadoServer.egg-info/top_level.txt