Metadata-Version: 1.0
Name: SimpleTornadoServer
Version: 0.1
Summary: better SimpleHTTPServer using tornado
Home-page: https://github.com/imom0/SimpleTornadoServer
Author: iMom0
Author-email: mobeiheart@gmail.com
License: BSD
Platform: UNKNOWN
Classifier: Development Status :: 4 - Beta
Classifier: Environment :: Console
Classifier: Intended Audience :: Developers
Classifier: Intended Audience :: System Administrators
Classifier: License :: OSI Approved :: BSD License
Classifier: Topic :: Utilities
